OBP_security_pillar/__init__.py
OBP_security_pillar/compliance.py
OBP_security_pillar/elb_logging_enabled.py
OBP_security_pillar/elb_tls_https_listeners_only.py
OBP_security_pillar/guard_duty_enabled.py
OBP_security_pillar/lambda_inside_vpc.py
OBP_security_pillar/security_hub_enabled.py
OBP_security_pillar/auto_scaling/__init__.py
OBP_security_pillar/auto_scaling/launch_config_public_ip_disabled.py
OBP_security_pillar/cloudtrail/__init__.py
OBP_security_pillar/cloudtrail/cloudtrail_cloudwatch_logs_enabled.py
OBP_security_pillar/cloudtrail/driver.py
OBP_security_pillar/dynamodb/__init__.py
OBP_security_pillar/dynamodb/dynamodb_table_encrypted_kms.py
OBP_security_pillar/ec2/Incoming_ssh_disabled.py
OBP_security_pillar/ec2/__init__.py
OBP_security_pillar/ec2/ebs_snapshot_public_restorable_check.py
OBP_security_pillar/ec2/ec2_ebs_encryption_by_default.py
OBP_security_pillar/ec2/ec2_encrypted_volume.py
OBP_security_pillar/ec2/ec2_imdsv2_check.py
OBP_security_pillar/ec2/ec2_instance_managed_by_ssm.py
OBP_security_pillar/ec2/ec2_instance_multiple_eni_check.py
OBP_security_pillar/ec2/ec2_instance_profile_attached.py
OBP_security_pillar/ec2/ec2_volume_inuse_check.py
OBP_security_pillar/ec2/instance_in_vpc.py
OBP_security_pillar/ec2/vpc_flow_logs_enabled.py
OBP_security_pillar/rds/__init__.py
OBP_security_pillar/rds/rds_automatic_minor_version_upgrade_enabled.py
OBP_security_pillar/rds/rds_instance_public_access_check.py
OBP_security_pillar/rds/rds_snapshot_encrypted.py
OBP_security_pillar/rds/rds_snapshots_public_prohibited.py
OBP_security_pillar/rds/rds_storage_encrypted.py
OBP_security_pillar/s3/__init__.py
OBP_security_pillar/s3/s3_bucket_logging_enabled.py
OBP_security_pillar/s3/s3_bucket_public_read_prohibited.py
OBP_security_pillar/s3/s3_bucket_public_write_prohibited.py
OBP_security_pillar/s3/s3_bucket_server_side_encryption_enabled.py
OBP_security_pillar/s3/s3_bucket_ssl_requests_only.py
OBP_security_pillar/s3/s3_bucket_versioning_enabled.py
OBP_security_pillar-0.2.2.dist-info/METADATA
OBP_security_pillar-0.2.2.dist-info/WHEEL
OBP_security_pillar-0.2.2.dist-info/top_level.txt
OBP_security_pillar-0.2.2.dist-info/RECORD
