Metadata-Version: 2.1
Name: OBP-security-pillar
Version: 0.2.2
Summary: Provides AWS compliance details
Author-email: "dheeraj.banodha" <dheerajmbanodha@gmail.com>
Classifier: Programming Language :: Python :: 3
Classifier: Operating System :: OS Independent
Requires-Python: >=3.7
Requires-Dist: boto3
Requires-Dist: pytz
